tvb_liteline/__init__.py
tvb_liteline/_modidx.py
tvb_liteline/core.py
tvb_liteline/models.py
tvb_liteline-0.0.1.dist-info/LICENSE
tvb_liteline-0.0.1.dist-info/METADATA
tvb_liteline-0.0.1.dist-info/WHEEL
tvb_liteline-0.0.1.dist-info/entry_points.txt
tvb_liteline-0.0.1.dist-info/top_level.txt
tvb_liteline-0.0.1.dist-info/RECORD
